ai_dungeon_cli/__init__.py
ai_dungeon_cli/opening-ascii.txt
ai_dungeon_cli/opening-utf8.txt
ai_dungeon_cli-0.2.0.dist-info/LICENSE
ai_dungeon_cli-0.2.0.dist-info/METADATA
ai_dungeon_cli-0.2.0.dist-info/WHEEL
ai_dungeon_cli-0.2.0.dist-info/entry_points.txt
ai_dungeon_cli-0.2.0.dist-info/top_level.txt
ai_dungeon_cli-0.2.0.dist-info/RECORD
