Metadata-Version: 2.1
Name: ai-dungeon-cli
Version: 0.2.0
Summary: Play ai dungeon from your terminal
Home-page: https://github.com/Eigenbahn/ai-dungeon-cli
Author: Jordan Besly
Author-email: 
License: UNKNOWN
Platform: UNKNOWN
Classifier: Programming Language :: Python :: 3
Classifier: License :: OSI Approved :: MIT License
Requires-Python: >=3.3
Requires-Dist: requests (>=2.23.0)
Requires-Dist: PyYAML (>=5.1.2)
Requires-Dist: pyreadline (>=2.1) ; platform_system == "Windows"
